{
  "type": "FeatureCollection", 
  "features": [
    {
      "geometry": {
        "type": "Point", 
        "coordinates": [
          -104.999839, 
          39.74925566
        ]
      }, 
      "type": "Feature", 
      "properties": {
        "name": "Steve Kinney", 
        "url": "http://twitter.com/stevekinney/status/592719484970004481", 
        "text": "@samselikoff I didn\u2019t miss you at #railsconf, did I?", 
        "created_at": "Mon Apr 27 15:58:32 +0000 2015", 
        "profile_image_url": "http://pbs.twimg.com/profile_images/565704816412745728/eLljaYJG_normal.jpeg", 
        "screen_name": "stevekinney"
      }
    }, 
    {
      "geometry": {
        "type": "Point", 
        "coordinates": [
          -104.99983407, 
          39.74927182
        ]
      }, 
      "type": "Feature", 
      "properties": {
        "name": "Steve Kinney", 
        "url": "http://twitter.com/stevekinney/status/592715330130190338", 
        "text": "I didn\u2019t hear a single word about Angular at #railsconf. @emberjs &amp; @reactjs had sessions and got mentioned during the keynotes.", 
        "created_at": "Mon Apr 27 15:42:01 +0000 2015", 
        "profile_image_url": "http://pbs.twimg.com/profile_images/565704816412745728/eLljaYJG_normal.jpeg", 
        "screen_name": "stevekinney"
      }
    }
  ]
}
